litelines/__init__.py
litelines/build_dfa.py
litelines/build_regex.py
litelines/draw_dfa.py
litelines/utils.py
litelines/transformers/__init__.py
litelines/transformers/schemaprocessor.py
litelines-0.1.5.dist-info/METADATA
litelines-0.1.5.dist-info/WHEEL
litelines-0.1.5.dist-info/licenses/LICENSE
litelines-0.1.5.dist-info/RECORD
