Metadata-Version: 2.4
Name: litelines
Version: 0.1.5
Summary: Customize, control, and enhance LLM generation with logits processors, featuring visualization capabilities to inspect and understand state transitions
License-File: LICENSE
Requires-Python: >=3.8
Requires-Dist: outlines-core>=0.2.9
